traceplot/BackgroundImage.py
traceplot/Trace.py
traceplot/__init__.py
traceplot/py.typed
traceplot/helpers/__init__.py
traceplot/helpers/greet.py
traceplot/helpers/geo/__init__.py
traceplot/helpers/gmaps/__init__.py
traceplot/helpers/graph/__init__.py
traceplot/map_providers/Gmaps.py
traceplot/map_providers/MapProvider.py
traceplot/map_providers/__init__.py
traceplot/types/__init__.py
traceplot-1.0.4.dist-info/METADATA
traceplot-1.0.4.dist-info/WHEEL
traceplot-1.0.4.dist-info/RECORD
