Metadata-Version: 2.4
Name: traceplot
Version: 1.0.4
Summary: Static map generator with points plots.
Project-URL: Homepage, https://github.com/cdugeai/traceplot
Project-URL: Issues, https://github.com/cdugeai/traceplot/issues
Author-email: Colin Dugeai <colin.dugeai@gmail.com>
Requires-Python: >=3.12
Requires-Dist: matplotlib>=3.10.3
Requires-Dist: pyproj>=3.7.1
Requires-Dist: requests>=2.32.4
